<?xml version="1.0" encoding="utf-8" ?>
<dwsync>
<file name="bootstrap.min.js" server="ftp.zmessenger.info" local="131444850020298576" remote="131447808000000000" Dst="0" />
<file name="scrolling-nav.js" server="ftp.zmessenger.info" local="131357632435246376" remote="131447808000000000" Dst="0" />
<file name="jquery.easing.min.js" server="ftp.zmessenger.info" local="131357632410847727" remote="131447808000000000" Dst="0" />
<file name="functions.js" server="ftp.zmessenger.info" local="131442256039263583" remote="131447823600000000" Dst="0" />
<file name="jquery-2.1.3.min.js" server="ftp.zmessenger.info" local="131442193334867730" remote="131447823600000000" Dst="0" />
<file name="jquery.js" server="ftp.zmessenger.info" local="131354335904518892" remote="131447829600000000" Dst="0" />
<file name="modernizr.custom.86080.js" server="ftp.zmessenger.info" local="131453553688738660" remote="131453143200000000" Dst="0" />
<file name="skillup_anaytics.js" server="ftp.zmessenger.info" local="131454367647353829" remote="131453953200000000" Dst="0" />
</dwsync>